miniml/__init__.py
miniml/ann/ANN.py
miniml/ann/__init__.py
miniml/ann/common.py
miniml/ann/utils.py
miniml/decomposition/PCA.py
miniml/decomposition/__init__.py
miniml/helper/BasePlot.py
miniml/helper/__init__.py
miniml/kmeans/KMeans.py
miniml/kmeans/__init__.py
miniml/knn/KNearestNeighborsClassifier.py
miniml/knn/KNearestNeighborsRegressor.py
miniml/knn/__init__.py
miniml/minisvm/AlgebraicSVC.py
miniml/minisvm/MultiSVC.py
miniml/minisvm/Plot.py
miniml/minisvm/SMoSVC.py
miniml/minisvm/SMoSVR.py
miniml/minisvm/__init__.py
miniml/mse/MSeClassifier.py
miniml/mse/MSeRegressor.py
miniml/mse/__init__.py
miniml/nearestmean/NearestMean.py
miniml/nearestmean/__init__.py
miniml/perceptron/Perceptron.py
miniml/perceptron/__init__.py
miniml/ridge/Ridge.py
miniml/ridge/__init__.py
MLplayground-1.0.1.dist-info/METADATA
MLplayground-1.0.1.dist-info/WHEEL
MLplayground-1.0.1.dist-info/top_level.txt
MLplayground-1.0.1.dist-info/RECORD
