Metadata-Version: 2.1
Name: MLplayground
Version: 1.0.1
Summary: A mini Machine Learning Algorithm Library
Home-page: https://lujiazho.github.io/
Author: LujiaZhong
Author-email: UNKNOWN
License: MIT License
Platform: Windows 10
Classifier: Intended Audience :: Developers
Classifier: Operating System :: OS Independent
Classifier: Natural Language :: English
Classifier: Programming Language :: Python :: 3.7
Classifier: Topic :: Software Development :: Libraries
Requires-Dist: numpy (==1.21.1)
Requires-Dist: matplotlib (==3.5.1)
